{
  "Prefix": "<color=#D85540>[Blueprint Deling]</color> ",
  "ArgumentsError": "Feil bruk av kommando. Prøv <color=#ffff00>/bs help</color>.",
  "Help": "<color=#D85540>Blueprint Delingskommandoer:</color>\n<color=#D85540>/bs toggle</color> - Slå av/på automatisk blueprint deling\n<color=#D85540>/bs share <player></color> - Del dine lærte blueprints med en spiller\n<color=#D85540>/bs show <team|clan|friend> [navn]</color> - Vis blueprints delt med deg\n<color=#D85540>/bs help</color> - Vis denne hjelpen",
  "ToggleOn": "Blueprint deling er nå <color=#00ff00>aktivert</color>.",
  "ToggleOff": "Blueprint deling er nå <color=#ff0000>deaktivert</color>.",
  "NoPermission": "Du har ikke tillatelse til å bruke denne kommandoen.",
  "CannotShare": "Du kan ikke dele blueprints med denne spilleren, de må være i teamet, klanen, eller vennelisten din.",
  "NoTarget": "Du må spesifisere en spiller å dele med.",
  "TargetEqualsPlayer": "Du kan ikke dele blueprints med deg selv.",
  "PlayerNotFound": "Spiller ikke funnet.",
  "PlayerSharedBlueprints": "Du delte <color=#ffff00>{0}</color> blueprint(s) med <color=#ffff00>{1}</color>.",
  "TargetLearntBlueprints": "<color=#ffff00>{0}</color> har delt <color=#ffff00>{1}</color> blueprint(s) med deg.",
  "NoBlueprintsToShare": "Du har ingen nye blueprints å dele med <color=#ffff00>{0}</color>.",
  "PlayerSharedBlueprint": "Du har lært <color=#ffff00>{0}</color> blueprint og delt det med <color=#ffff00>{1}</color> spiller(e).",
  "TargetLearntBlueprint": "<color=#ffff00>{0}</color> har delt <color=#ffff00>{1}</color> blueprint med deg.",
  "BlueprintBlocked": "<color=#ffff00>{0}</color> blueprint er blokkert fra deling, men du har fortsatt lært det.",
  "TargetSharingDisabled": "Kan ikke dele blueprints med <color=#ffff00>{0}</color> – de har deaktivert deling.",
  "BlueprintsRemoved": "Du har mistet tilgangen til <color=#ffff00>{0}</color> blueprint(s).",
  "ShowMissingArgument": "Du må spesifisere hvilke delte blueprints du vil se. Valg: <color=#ffff00>team</color>, <color=#ffff00>clan</color>, eller <color=#ffff00>friend</color>.",
  "ShowFriendArgumentMissing": "Du må spesifisere navnet til en venn.",
  "NotFriends": "Du er ikke venner med denne spilleren.",
  "NoSharedBlueprints": "Ingen blueprints har blitt delt med deg.",
  "SharedBlueprintsTitle": "Blueprints Delt Med Deg:",
  "ShowSharedBlueprints": "<color=#ffff00>Tier {0}:</color> {1}",
  "LoseBlueprintsDisabled": "Denne funksjonen har blitt deaktivert av serveradministratoren."
}